eggfarm/__init__.py
eggfarm/main.py
eggfarm/table_func_generator.py
eggfarm/templates/Makefile.template
eggfarm/templates/README.template.md
eggfarm/templates/__init__.py
eggfarm/templates/func/__init__.template.py
eggfarm/templates/func/info.template.toml
eggfarm/templates/func/version.template.py
eggfarm/templates/pyproject.template.toml
eggfarm/templates/tests/func_test.template.py
eggfarm/templates/tests/supported_signature_list.template.py
eggfarm-0.2.0.dist-info/METADATA
eggfarm-0.2.0.dist-info/WHEEL
eggfarm-0.2.0.dist-info/entry_points.txt
eggfarm-0.2.0.dist-info/RECORD
