Metadata-Version: 2.1
Name: eggfarm
Version: 0.2.0
Summary: A tool for generating stonewave table function
Author: Yue Ni
Author-email: niyue.com@gmail.com
Requires-Python: >=3.9,<4.0
Classifier: Programming Language :: Python :: 3
Classifier: Programming Language :: Python :: 3.9
Classifier: Programming Language :: Python :: 3.10
Classifier: Programming Language :: Python :: 3.11
Classifier: Programming Language :: Python :: 3.12
Classifier: Programming Language :: Python :: 3.13
Requires-Dist: Jinja2 (>=2.11.3,<3.0.0)
Requires-Dist: MarkupSafe (==2.0.1)
